{
    "clk": [
        140080.0,
        40460.0
    ],
    "req_msg[0]": [
        80830.0,
        140.0
    ],
    "req_msg[10]": [
        140080.0,
        95340.0
    ],
    "req_msg[11]": [
        140080.0,
        83020.0
    ],
    "req_msg[12]": [
        140080.0,
        69580.0
    ],
    "req_msg[13]": [
        140080.0,
        67340.0
    ],
    "req_msg[14]": [
        140080.0,
        58380.0
    ],
    "req_msg[15]": [
        140080.0,
        46060.0
    ],
    "req_msg[16]": [
        76350.0,
        140.0
    ],
    "req_msg[17]": [
        64030.0,
        140.0
    ],
    "req_msg[18]": [
        59550.0,
        140.0
    ],
    "req_msg[19]": [
        140.0,
        51660.0
    ],
    "req_msg[1]": [
        67390.0,
        140.0
    ],
    "req_msg[20]": [
        140.0,
        61740.0
    ],
    "req_msg[21]": [
        140.0,
        76300.0
    ],
    "req_msg[22]": [
        140.0,
        95340.0
    ],
    "req_msg[23]": [
        44990.0,
        139860.0
    ],
    "req_msg[24]": [
        64030.0,
        139860.0
    ],
    "req_msg[25]": [
        140.0,
        67340.0
    ],
    "req_msg[26]": [
        92030.0,
        139860.0
    ],
    "req_msg[27]": [
        140080.0,
        81900.0
    ],
    "req_msg[28]": [
        140080.0,
        68460.0
    ],
    "req_msg[29]": [
        72990.0,
        140.0
    ],
    "req_msg[2]": [
        55070.0,
        140.0
    ],
    "req_msg[30]": [
        140080.0,
        57260.0
    ],
    "req_msg[31]": [
        92030.0,
        140.0
    ],
    "req_msg[3]": [
        43870.0,
        140.0
    ],
    "req_msg[4]": [
        140.0,
        60620.0
    ],
    "req_msg[5]": [
        140.0,
        71820.0
    ],
    "req_msg[6]": [
        140.0,
        86380.0
    ],
    "req_msg[7]": [
        52830.0,
        139860.0
    ],
    "req_msg[8]": [
        65150.0,
        139860.0
    ],
    "req_msg[9]": [
        140.0,
        75180.0
    ],
    "req_rdy": [
        140.0,
        102060.0
    ],
    "req_val": [
        77470.0,
        139860.0
    ],
    "reset": [
        75230.0,
        139860.0
    ],
    "resp_msg[0]": [
        78590.0,
        140.0
    ],
    "resp_msg[10]": [
        90910.0,
        139860.0
    ],
    "resp_msg[11]": [
        140080.0,
        84140.0
    ],
    "resp_msg[12]": [
        140080.0,
        71820.0
    ],
    "resp_msg[13]": [
        140080.0,
        66220.0
    ],
    "resp_msg[14]": [
        140080.0,
        59500.0
    ],
    "resp_msg[15]": [
        140080.0,
        56140.0
    ],
    "resp_msg[1]": [
        70750.0,
        140.0
    ],
    "resp_msg[2]": [
        57310.0,
        140.0
    ],
    "resp_msg[3]": [
        140.0,
        52780.0
    ],
    "resp_msg[4]": [
        140.0,
        63980.0
    ],
    "resp_msg[5]": [
        140.0,
        70700.0
    ],
    "resp_msg[6]": [
        140.0,
        88620.0
    ],
    "resp_msg[7]": [
        140.0,
        87500.0
    ],
    "resp_msg[8]": [
        67390.0,
        139860.0
    ],
    "resp_msg[9]": [
        68510.0,
        139860.0
    ],
    "resp_rdy": [
        74110.0,
        139860.0
    ],
    "resp_val": [
        76350.0,
        139860.0
    ]
}